pelican/plugins/gesetz/__init__.py
pelican_gesetze-0.1.0.dist-info/LICENSE
pelican_gesetze-0.1.0.dist-info/WHEEL
pelican_gesetze-0.1.0.dist-info/METADATA
pelican_gesetze-0.1.0.dist-info/RECORD
